funlogger/__init__.py
funlogger/__version__.py
funlogger/config.py
funlogger-1.0.2.dist-info/METADATA
funlogger-1.0.2.dist-info/WHEEL
funlogger-1.0.2.dist-info/licenses/LICENSE
funlogger-1.0.2.dist-info/RECORD
