Metadata-Version: 2.4
Name: funlogger
Version: 1.0.2
Author-email: wangpeng <wangpengb@uniontech.com>
License: GPL2.0
License-File: LICENSE
Requires-Python: >=3.6
Requires-Dist: colorama
